plonemeeting/__init__.py
plonemeeting/portal/__init__.py
plonemeeting/portal/core/__init__.py
plonemeeting/portal/core/adapters.py
plonemeeting/portal/core/adapters.zcml
plonemeeting/portal/core/cache.py
plonemeeting/portal/core/config.py
plonemeeting/portal/core/configure.zcml
plonemeeting/portal/core/interfaces.py
plonemeeting/portal/core/patches.py
plonemeeting/portal/core/permissions.zcml
plonemeeting/portal/core/setuphandlers.py
plonemeeting/portal/core/sync_utils.py
plonemeeting/portal/core/testing.py
plonemeeting/portal/core/utils.py
plonemeeting/portal/core/vocabularies.py
plonemeeting/portal/core/behaviors/autopublish.py
plonemeeting/portal/core/behaviors/configure.zcml
plonemeeting/portal/core/browser/__init__.py
plonemeeting/portal/core/browser/colors.py
plonemeeting/portal/core/browser/configure.zcml
plonemeeting/portal/core/browser/contact_info.py
plonemeeting/portal/core/browser/docgen.py
plonemeeting/portal/core/browser/footer.py
plonemeeting/portal/core/browser/homepage.py
plonemeeting/portal/core/browser/institution.py
plonemeeting/portal/core/browser/item.py
plonemeeting/portal/core/browser/manage_users.py
plonemeeting/portal/core/browser/meeting.py
plonemeeting/portal/core/browser/nextprevious.py
plonemeeting/portal/core/browser/publication.py
plonemeeting/portal/core/browser/sitemap.py
plonemeeting/portal/core/browser/sync.py
plonemeeting/portal/core/browser/utils.py
plonemeeting/portal/core/browser/overrides/.gitkeep
plonemeeting/portal/core/browser/overrides/Products.CMFPlone.browser.templates.colophon.pt
plonemeeting/portal/core/browser/overrides/eea.facetednavigation.widgets.text.widget.pt
plonemeeting/portal/core/browser/overrides/plone.app.contenttypes.browser.templates.file.pt
plonemeeting/portal/core/browser/overrides/plone.batching.batchnavigation.pt
plonemeeting/portal/core/browser/resources/.eslintrc.json
plonemeeting/portal/core/browser/resources/.prettierrc.json
plonemeeting/portal/core/browser/resources/Makefile
plonemeeting_portal_core-2.2.6.dist-info/licenses/LICENSE.GPL
plonemeeting_portal_core-2.2.6.dist-info/licenses/LICENSE.rst
plonemeeting_portal_core-2.2.6.dist-info/METADATA
plonemeeting_portal_core-2.2.6.dist-info/WHEEL
plonemeeting_portal_core-2.2.6.dist-info/entry_points.txt
plonemeeting_portal_core-2.2.6.dist-info/top_level.txt
plonemeeting_portal_core-2.2.6.dist-info/RECORD
