Metadata-Version: 2.4
Name: plonemeeting.portal.core
Version: 2.2.6
Summary: Plonemeeting decisions publication portal
Home-page: https://github.com/collective/plonemeeting.portal.core
Author: Laurent Lasudry
Author-email: laurent.lasudry@affinitic.be
License: GPL version 2
Project-URL: PyPI, https://pypi.python.org/pypi/plonemeeting.portal.core
Project-URL: Source, https://github.com/collective/plonemeeting.portal.core
Project-URL: Tracker, https://github.com/collective/plonemeeting.portal.core/issues
Keywords: Python Plone
Classifier: Environment :: Web Environment
Classifier: Framework :: Plone
Classifier: Framework :: Plone :: Addon
Classifier: Framework :: Plone :: 6.1
Classifier: Programming Language :: Python
Classifier: Programming Language :: Python :: 3.11
Classifier: Programming Language :: Python :: 3.12
Classifier: Operating System :: OS Independent
Classifier: License :: OSI Approved :: GNU General Public License v2 (GPLv2)
Requires-Python: >=3.11
License-File: LICENSE.GPL
License-File: LICENSE.rst
Requires-Dist: setuptools
Requires-Dist: collective.fingerpointing
Requires-Dist: collective.timestamp
Requires-Dist: collective.autopublishing
Requires-Dist: collective.documentgenerator>=4.0
Requires-Dist: collective.excelexport>=2.0
Requires-Dist: collective.exportimport
Requires-Dist: collective.z3cform.datagridfield>=3.0.2
Requires-Dist: eea.facetednavigation>=16.2
Requires-Dist: natsort
Requires-Dist: plone.api>=2.1.0
Requires-Dist: plone.app.dexterity
Requires-Dist: plone.formwidget.hcaptcha>=1.0.3
Requires-Dist: plone.restapi
Requires-Dist: requests
Requires-Dist: z3c.jbot
Requires-Dist: imio.helpers>=1.0.0rc2
Requires-Dist: imio.migrator>=1.34
Requires-Dist: imio.pyutils
Requires-Dist: rich
Requires-Dist: shutup
Requires-Dist: importlib-metadata
Provides-Extra: test
Requires-Dist: plone.app.testing; extra == "test"
Requires-Dist: plone.testing>=5.0.0; extra == "test"
Requires-Dist: plone.app.contenttypes; extra == "test"
Requires-Dist: plone.app.robotframework[test]; extra == "test"
Requires-Dist: mockito; extra == "test"
Dynamic: author
Dynamic: author-email
Dynamic: classifier
Dynamic: description
Dynamic: description-content-type
Dynamic: home-page
Dynamic: keywords
Dynamic: license
Dynamic: license-file
Dynamic: project-url
Dynamic: provides-extra
Dynamic: requires-dist
Dynamic: requires-python
Dynamic: summary
